spine_json_lib/__init__.py
spine_json_lib/spine_animation_editor.py
spine_json_lib/spine_graph_container.py
spine_json_lib/utils.py
spine_json_lib/data/__init__.py
spine_json_lib/data/constants.py
spine_json_lib/data/spine_anim_data.py
spine_json_lib/data/spine_exceptions.py
spine_json_lib/data/spine_version_type.py
spine_json_lib/data/data_types/__init__.py
spine_json_lib/data/data_types/animation.py
spine_json_lib/data/data_types/base_type.py
spine_json_lib/data/data_types/bone.py
spine_json_lib/data/data_types/deform.py
spine_json_lib/data/data_types/draworder.py
spine_json_lib/data/data_types/events.py
spine_json_lib/data/data_types/ik.py
spine_json_lib/data/data_types/path.py
spine_json_lib/data/data_types/skin.py
spine_json_lib/data/data_types/slot.py
spine_json_lib/data/data_types/transform.py
spine_json_lib/deserializer/__init__.py
spine_json_lib/deserializer/spine_nodes.py
spine_json_lib/deserializer/test/__init__.py
spine_json_lib/deserializer/test/test_spine_graph.py
spine_json_lib/graph/__init__.py
spine_json_lib/graph/dagraph.py
spine_json_lib/graph/factories.py
spine_json_lib/graph/graph_validator.py
spine_json_lib/graph/spamnode.py
spine_json_lib/graph/test/__init__.py
spine_json_lib/graph/test/test_graph.py
spine_json_lib/test/__init__.py
spine_json_lib/test/test_spine_animation_editor.py
spine_json_lib/test/test_utils.py
spine_json_lib-0.4.6.dist-info/AUTHORS.rst
spine_json_lib-0.4.6.dist-info/LICENSE
spine_json_lib-0.4.6.dist-info/METADATA
spine_json_lib-0.4.6.dist-info/WHEEL
spine_json_lib-0.4.6.dist-info/entry_points.txt
spine_json_lib-0.4.6.dist-info/top_level.txt
spine_json_lib-0.4.6.dist-info/RECORD
