Metadata-Version: 2.1
Name: spine-json-lib
Version: 0.4.6
Summary: Library to parse and edit spine animations from command line
Home-page: https://github.com/socialpoint-labs/spine-json-lib
Author: Jesus Diaz Gomez
Author-email: yisus.gamedev@gmail.com
License: MIT license
Keywords: spine_json_lib
Platform: UNKNOWN
Classifier: Development Status :: 5 - Production/Stable
Classifier: Intended Audience :: Developers
Classifier: License :: OSI Approved :: MIT License
Classifier: Natural Language :: English
Classifier: Programming Language :: Python :: 3
Classifier: Programming Language :: Python :: 3.6
Classifier: Programming Language :: Python :: 3.7
Classifier: Programming Language :: Python :: 3.8
Requires-Python: >=3.6
License-File: LICENSE
License-File: AUTHORS.rst
Provides-Extra: dev
Requires-Dist: flake8 (>=3.7.8) ; extra == 'dev'
Requires-Dist: tox (>=3.14.0) ; extra == 'dev'
Requires-Dist: coverage (>=4.5.4) ; extra == 'dev'
